aws_dbesdk_dynamodb/__init__.py
aws_dbesdk_dynamodb-0.0.1.dist-info/METADATA
aws_dbesdk_dynamodb-0.0.1.dist-info/WHEEL
aws_dbesdk_dynamodb-0.0.1.dist-info/top_level.txt
aws_dbesdk_dynamodb-0.0.1.dist-info/RECORD
